colorutill/__init__.py
colorutill-1.1.dist-info/METADATA
colorutill-1.1.dist-info/WHEEL
colorutill-1.1.dist-info/top_level.txt
colorutill-1.1.dist-info/RECORD
