Metadata-Version: 2.1
Name: colorutill
Version: 1.1
Summary: blindev
Author-email: <linuxdevelopers@gmail.com>
License: Eclipse Public License 2.0
